steyr/__init__.py
steyr/assemble.py
steyr/callbacks.py
steyr/cli.py
steyr/config.py
steyr/page.py
steyr/serve.py
steyr/styles.py
steyr-0.1.0.dist-info/licenses/LICENSE
steyr-0.1.0.dist-info/METADATA
steyr-0.1.0.dist-info/WHEEL
steyr-0.1.0.dist-info/entry_points.txt
steyr-0.1.0.dist-info/top_level.txt
steyr-0.1.0.dist-info/RECORD
