Metadata-Version: 2.4
Name: steyr
Version: 0.1.0
Summary: Simple, templated static site generator
Author-email: Mohamad Makki <moe.m.makki@gmail.com>
License-Expression: 0BSD
Requires-Python: >=3.13
License-File: LICENSE
Requires-Dist: feedgen>=1.0.0
Requires-Dist: jinja2>=3.1.6
Requires-Dist: latex2mathml>=3.78.0
Requires-Dist: livereload>=2.7.1
Requires-Dist: pulldown-cmark>=0.1.1
Requires-Dist: pydantic>=2.11.7
Requires-Dist: pygments>=2.19.2
Dynamic: license-file
